odoo/addons/agreement_account/README.rst
odoo/addons/agreement_account/__init__.py
odoo/addons/agreement_account/__manifest__.py
odoo/addons/agreement_account/i18n/agreement_account.pot
odoo/addons/agreement_account/models/__init__.py
odoo/addons/agreement_account/models/account_invoice.py
odoo/addons/agreement_account/models/agreement.py
odoo/addons/agreement_account/readme/CONTRIBUTORS.rst
odoo/addons/agreement_account/readme/DESCRIPTION.rst
odoo/addons/agreement_account/security/ir.model.access.csv
odoo/addons/agreement_account/static/description/icon.png
odoo/addons/agreement_account/static/description/index.html
odoo/addons/agreement_account/views/account_invoice.xml
odoo/addons/agreement_account/views/agreement.xml
odoo12_addon_agreement_account-12.0.1.0.0.99.dev3.dist-info/METADATA
odoo12_addon_agreement_account-12.0.1.0.0.99.dev3.dist-info/WHEEL
odoo12_addon_agreement_account-12.0.1.0.0.99.dev3.dist-info/top_level.txt
odoo12_addon_agreement_account-12.0.1.0.0.99.dev3.dist-info/RECORD
